scientific_colormaps/__init__.py
scientific_colourmaps/__init__.py
scientific_colourmaps/__pycache__/__init__.cpython-36.pyc
scientific_colourmaps/__pycache__/__init__.cpython-37.pyc
scientific_colourmaps-1.0b0.dist-info/METADATA
scientific_colourmaps-1.0b0.dist-info/WHEEL
scientific_colourmaps-1.0b0.dist-info/top_level.txt
scientific_colourmaps-1.0b0.dist-info/RECORD
