Metadata-Version: 2.1
Name: scientific-colourmaps
Version: 1.0b0
Summary: Fabio Crameri's scientific colourmaps
Home-page: https://github.com/gwerbin/scientific-colourmaps
Author: Gregory Werbin
Author-email: outthere@me.gregwerbin.com
License: MIT
Project-URL: Bug Tracker, https://github.com/gwerbin/scientific-colourmaps/issues
Project-URL: Documentation, https://github.com/gwerbin/scientific-colourmaps/blob/master/python/README.md
Project-URL: Source Code, https://github.com/gwerbin/scientific-colourmaps
Platform: UNKNOWN
Requires-Python: >= 3
Requires-Dist: matplotlib
Requires-Dist: setuptools
